saltfm/__init__.py
saltfm/config.py
saltfm/exceptions.py
saltfm/log.py
saltfm-0.0.4.data/data/share/saltfm/README.rst
saltfm-0.0.4.data/data/share/saltfm/config.yaml.sample
saltfm-0.0.4.data/scripts/saltfm
saltfm-0.0.4.dist-info/DESCRIPTION.rst
saltfm-0.0.4.dist-info/METADATA
saltfm-0.0.4.dist-info/RECORD
saltfm-0.0.4.dist-info/WHEEL
saltfm-0.0.4.dist-info/metadata.json
saltfm-0.0.4.dist-info/top_level.txt
