Metadata-Version: 2.0
Name: saltfm
Version: 0.0.4
Summary: Salt Formula Manager
Home-page: https://github.com/hvnsweeting/saltfm
Author: Viet Hung Nguyen
Author-email: hvn@familug.org
License: MIT
Platform: UNKNOWN
Classifier: Environment :: Console
Classifier: Topic :: Terminals :: Terminal Emulators/X Terminals
